cap_from_youtube/__init__.py
cap_from_youtube/cap_from_youtube.py
cap_from_youtube_opts-0.0.10.1.dist-info/METADATA
cap_from_youtube_opts-0.0.10.1.dist-info/WHEEL
cap_from_youtube_opts-0.0.10.1.dist-info/top_level.txt
cap_from_youtube_opts-0.0.10.1.dist-info/RECORD
