Metadata-Version: 2.1
Name: cap-from-youtube-opts
Version: 0.0.10.1
Summary: Get an OpenCV video capture from an YouTube video URL + ydl_opts
Home-page: https://github.com/ogre0382/cap_from_youtube_opts
Author: ogre0382
License: MIT
Requires-Dist: numpy
Requires-Dist: opencv-python
Requires-Dist: yt-dlp
